Metadata-Version: 1.0
Name: cmdpack
Version: 0.5.2
Summary: cmd run packages
Home-page: http://github.com/jeppeter/cmdpack
Author: jeppeter Wang
Author-email: jeppeter@gmail.com
License: MIT
Platform: UNKNOWN
